odoo10_addon_product_analytic_donation-10.0.1.0.0.99.dev4-py2.7-nspkg.pth
odoo/addons/product_analytic_donation/README.rst
odoo/addons/product_analytic_donation/__init__.py
odoo/addons/product_analytic_donation/__manifest__.py
odoo/addons/product_analytic_donation/i18n/de.po
odoo/addons/product_analytic_donation/i18n/product_analytic_donation.pot
odoo/addons/product_analytic_donation/models/__init__.py
odoo/addons/product_analytic_donation/models/donation_line.py
odoo/addons/product_analytic_donation/static/description/icon.png
odoo/addons/product_analytic_donation/tests/__init__.py
odoo/addons/product_analytic_donation/tests/test_donation.py
odoo10_addon_product_analytic_donation-10.0.1.0.0.99.dev4.dist-info/METADATA
odoo10_addon_product_analytic_donation-10.0.1.0.0.99.dev4.dist-info/RECORD
odoo10_addon_product_analytic_donation-10.0.1.0.0.99.dev4.dist-info/WHEEL
odoo10_addon_product_analytic_donation-10.0.1.0.0.99.dev4.dist-info/namespace_packages.txt
odoo10_addon_product_analytic_donation-10.0.1.0.0.99.dev4.dist-info/top_level.txt
