Metadata-Version: 2.1
Name: odoo10-addon-product-analytic-donation
Version: 10.0.1.0.0.99.dev4
Summary: Glue module between donation and product_analytic
Home-page: http://www.akretion.com
Author: Akretion, Odoo Community Association (OCA)
Author-email: support@odoo-community.org
License: AGPL-3
Platform: UNKNOWN
Classifier: Programming Language :: Python
Classifier: Framework :: Odoo
Classifier: License :: OSI Approved :: GNU Affero General Public License v3
Requires-Python: ~=2.7
Requires-Dist: odoo10-addon-donation
Requires-Dist: odoo10-addon-product-analytic
Requires-Dist: odoo (<10.1dev,>=10.0)
